flickrsets
