Metadata-Version: 1.0
Name: django-flickrsets
Version: 0.1.6
Summary: Reusable Django application to synchronize Flickr sets.
Home-page: http://github.com/gillesfabio/django-flickrsets
Author: Gilles Fabio
Author-email: gilles.fabio@gmail.com
License: BSD
Keywords: django,flickr,sets,flickrsets,photo
Platform: UNKNOWN
Classifier: Development Status :: 4 - Beta
Classifier: Environment :: Web Environment
Classifier: Intended Audience :: Developers
Classifier: License :: OSI Approved :: BSD License
Classifier: Operating System :: OS Independent
Classifier: Programming Language :: Python
Classifier: Framework :: Django
